cassoulet.py
cassoulet/cassoulet.py
cassoulet-1.dist-info/METADATA
cassoulet-1.dist-info/WHEEL
cassoulet-1.dist-info/entry_points.txt
cassoulet-1.dist-info/top_level.txt
cassoulet-1.dist-info/RECORD
