Metadata-Version: 2.1
Name: cassoulet
Version: 1
Summary: A delicious terroir meal
Author: Mathias Bochet and Thomas Corno
